eight_ball/__init__.py
eight_ball/decorators.py
eight_ball-3.0.3.dist-info/LICENSE
eight_ball-3.0.3.dist-info/METADATA
eight_ball-3.0.3.dist-info/WHEEL
eight_ball-3.0.3.dist-info/top_level.txt
eight_ball-3.0.3.dist-info/RECORD
